<manifest alg="2" build="2018.1.1.386" opt="false" iceEnabled="true" iceMarkupVersion="2" iceEnabledOptions="link,responsive,cachebuster,textStyling" exportTarget="other" domain="bigsmokelasvegas.com" resolutions="1x,2x" timestamp="1689699833328">
  <folder name="css">
    <file name="site_global.css" crc="91036504"/>
    <file name="master_a-master.css" crc="193577884" ref="index:faq"/>
    <file name="nomq_preview_master_a-master.css" crc="433669822" ref="index:faq"/>
    <file name="index.css" crc="118597293" ref="index"/>
    <file name="nomq_index.css" crc="509216073" ref="index"/>
    <file name="faq.css" crc="507395071" ref="faq"/>
    <file name="nomq_faq.css" crc="3934803245" ref="faq"/>
  </folder>
  <folder name="fonts">
    <file name="worksans-bold.woff" crc="180089418"/>
    <file name="worksans-bold.eot" crc="4098374513"/>
    <file name="worksans-regular.woff" crc="283533100"/>
    <file name="worksans-regular.eot" crc="480645326"/>
  </folder>
  <folder name="assets">
    <file name="bslv21_floorplan.pdf" crc="3779814306" seo="true" mt="1635959157000"/>
  </folder>
  <folder name="scripts">
    <file name="jquery-1.8.3.min.js" crc="209076791" ref="index:faq"/>
    <file name="museutils.js" crc="3939489907" ref="index:faq"/>
    <file name="whatinput.js" crc="86476730" ref="index:faq"/>
    <file name="museconfig.js" crc="3936894949" ref="index:faq"/>
    <file name="jquery.watch.js" crc="522499760" ref="index:faq"/>
    <file name="jquery.museresponsive.js" crc="95814420" ref="index:faq"/>
    <file name="require.js" crc="4177726516" ref="index:faq"/>
    <file name="webpro.js" crc="3856315280" ref="index:faq"/>
    <file name="musewpdisclosure.js" crc="4294234138" ref="index:faq"/>
    <file name="jquery.musepolyfill.bgsize.js" crc="85124417" ref="faq:index"/>
  </folder>
  <folder name="images">
    <file name="a-master-favicon.ico" crc="4228198005" ref="index:faq"/>
    <file name="logos731x1178.jpg" crc="4289896577" seo="true" ref="index">
      <caption webpage="index" alt=""/>
    </file>
    <file name="bot3images.jpg" crc="276659545" seo="true" ref="index">
      <caption webpage="index" alt=""/>
    </file>
    <file name="logos-mobile-crop-u47102.jpg" crc="3853360962" seo="true" ref="index">
      <caption webpage="index" alt=""/>
    </file>
    <file name="logos624x1005.jpg" crc="4282781565" seo="true" ref="index">
      <caption webpage="index" alt=""/>
    </file>
    <file name="bot3images1024x252.jpg" crc="4074423978" seo="true" ref="index">
      <caption webpage="index" alt=""/>
    </file>
    <file name="logos-mobile-crop-u471022.jpg" crc="3840558607" seo="true" ref="index">
      <caption webpage="index" alt=""/>
    </file>
    <file name="logos645x1039.jpg" crc="3894391729" seo="true" ref="index">
      <caption webpage="index" alt=""/>
    </file>
    <file name="bot3images960x236.jpg" crc="496706683" seo="true" ref="index">
      <caption webpage="index" alt=""/>
    </file>
    <file name="logos-mobile-crop-u471023.jpg" crc="446469341" seo="true" ref="index">
      <caption webpage="index" alt=""/>
    </file>
    <file name="logos632x1018.jpg" crc="4048783096" seo="true" ref="index">
      <caption webpage="index" alt=""/>
    </file>
    <file name="bot3images850x209.jpg" crc="3947919609" seo="true" ref="index">
      <caption webpage="index" alt=""/>
    </file>
    <file name="logos548x882.jpg" crc="102806914" seo="true" ref="index">
      <caption webpage="index" alt=""/>
    </file>
    <file name="bot3images768x189.jpg" crc="4251432150" seo="true" ref="index">
      <caption webpage="index" alt=""/>
    </file>
    <file name="logos517x834.jpg" crc="3862623437" seo="true" ref="index">
      <caption webpage="index" alt=""/>
    </file>
    <file name="bot3images667x164.jpg" crc="138357944" seo="true" ref="index">
      <caption webpage="index" alt=""/>
    </file>
    <file name="logos467x752.jpg" crc="232828181" seo="true" ref="index">
      <caption webpage="index" alt=""/>
    </file>
    <file name="bot3images568x140.jpg" crc="3977971713" seo="true" ref="index">
      <caption webpage="index" alt=""/>
    </file>
    <file name="bot3images-mobile414x938.jpg" crc="357269633" seo="true" ref="index">
      <caption webpage="index" alt=""/>
    </file>
    <file name="bot3images-mobile375x850.jpg" crc="3794481065" seo="true" ref="index">
      <caption webpage="index" alt=""/>
    </file>
    <file name="bot3images-mobile320x725.jpg" crc="3806333997" seo="true" ref="index">
      <caption webpage="index" alt=""/>
    </file>
    <file name="blank.gif" crc="4208392903" ref="index:faq"/>
    <file name="logos-mobile-crop-u47102_2x.jpg" crc="404453220" seo="true" ref="index">
      <caption webpage="index" alt=""/>
    </file>
    <file name="logos-mobile-crop-u47102_2x2.jpg" crc="134084737" seo="true" ref="index">
      <caption webpage="index" alt=""/>
    </file>
    <file name="logos-mobile-crop-u47102_2x3.jpg" crc="20854629" seo="true" ref="index">
      <caption webpage="index" alt=""/>
    </file>
    <file name="smoke4.png" crc="4133159776" seo="true" ref="index">
      <caption webpage="index" alt=""/>
      <caption webpage="index" alt=""/>
    </file>
    <file name="smoke4185x535.png" crc="295541815" seo="true" ref="index">
      <caption webpage="index" alt=""/>
    </file>
    <file name="smoke4173x501.png" crc="532063136" seo="true" ref="index">
      <caption webpage="index" alt=""/>
    </file>
    <file name="smoke4153x444.png" crc="243653043" seo="true" ref="index">
      <caption webpage="index" alt=""/>
    </file>
    <file name="smoke4139x401.png" crc="350380461" seo="true" ref="index">
      <caption webpage="index" alt=""/>
    </file>
    <file name="smoke4120x348.png" crc="66598501" seo="true" ref="index">
      <caption webpage="index" alt=""/>
    </file>
    <file name="smoke4103x297.png" crc="4091247051" seo="true" ref="index">
      <caption webpage="index" alt=""/>
    </file>
    <file name="23ticket-vip-fri.jpg" crc="3888394870" seo="true" ref="index">
      <caption webpage="index" alt=""/>
    </file>
    <file name="23ticket-vip-sat.jpg" crc="4290461419" seo="true" ref="index">
      <caption webpage="index" alt=""/>
    </file>
    <file name="23ticket-ga-fri.jpg" crc="3802425485" seo="true" ref="index">
      <caption webpage="index" alt=""/>
    </file>
    <file name="23ticket-ga-sat.jpg" crc="3914841616" seo="true" ref="index">
      <caption webpage="index" alt=""/>
    </file>
    <file name="resorts-world-2022.jpg" crc="3909192772" seo="true" ref="index">
      <caption webpage="index" alt=""/>
    </file>
    <file name="resorts-world-2022437x292.jpg" crc="4099149015" seo="true" ref="index">
      <caption webpage="index" alt=""/>
    </file>
    <file name="23ticket-vip-fri216x216.jpg" crc="3823910060" seo="true" ref="index">
      <caption webpage="index" alt=""/>
    </file>
    <file name="23ticket-vip-sat216x216.jpg" crc="4049852427" seo="true" ref="index">
      <caption webpage="index" alt=""/>
    </file>
    <file name="23ticket-ga-fri216x216.jpg" crc="3998840246" seo="true" ref="index">
      <caption webpage="index" alt=""/>
    </file>
    <file name="23ticket-ga-sat216x216.jpg" crc="4149722712" seo="true" ref="index">
      <caption webpage="index" alt=""/>
    </file>
    <file name="resorts-world-2022410x274.jpg" crc="196760330" seo="true" ref="index">
      <caption webpage="index" alt=""/>
    </file>
    <file name="23ticket-vip-fri176x176.jpg" crc="4021024288" seo="true" ref="index">
      <caption webpage="index" alt=""/>
      <caption webpage="index" alt=""/>
    </file>
    <file name="23ticket-vip-sat176x176.jpg" crc="513721339" seo="true" ref="index">
      <caption webpage="index" alt=""/>
      <caption webpage="index" alt=""/>
    </file>
    <file name="23ticket-ga-fri176x176.jpg" crc="152071342" seo="true" ref="index">
      <caption webpage="index" alt=""/>
      <caption webpage="index" alt=""/>
    </file>
    <file name="23ticket-ga-sat176x176.jpg" crc="3833389384" seo="true" ref="index">
      <caption webpage="index" alt=""/>
      <caption webpage="index" alt=""/>
    </file>
    <file name="resorts-world-2022363x242.jpg" crc="4116640542" seo="true" ref="index">
      <caption webpage="index" alt=""/>
    </file>
    <file name="23ticket-vip-fri170x170.jpg" crc="171390578" seo="true" ref="index">
      <caption webpage="index" alt=""/>
      <caption webpage="index" alt=""/>
    </file>
    <file name="23ticket-vip-sat170x170.jpg" crc="532321634" seo="true" ref="index">
      <caption webpage="index" alt=""/>
      <caption webpage="index" alt=""/>
    </file>
    <file name="23ticket-ga-fri170x170.jpg" crc="4198925747" seo="true" ref="index">
      <caption webpage="index" alt=""/>
      <caption webpage="index" alt=""/>
    </file>
    <file name="23ticket-ga-sat170x170.jpg" crc="271378892" seo="true" ref="index">
      <caption webpage="index" alt=""/>
      <caption webpage="index" alt=""/>
    </file>
    <file name="resorts-world-2022328x219.jpg" crc="4277984926" seo="true" ref="index">
      <caption webpage="index" alt=""/>
    </file>
    <file name="23ticket-vip-fri141x141.jpg" crc="3943064439" seo="true" ref="index">
      <caption webpage="index" alt=""/>
    </file>
    <file name="23ticket-vip-sat141x141.jpg" crc="524485046" seo="true" ref="index">
      <caption webpage="index" alt=""/>
    </file>
    <file name="23ticket-ga-fri141x141.jpg" crc="3853263949" seo="true" ref="index">
      <caption webpage="index" alt=""/>
    </file>
    <file name="23ticket-ga-sat141x141.jpg" crc="3992064008" seo="true" ref="index">
      <caption webpage="index" alt=""/>
    </file>
    <file name="resorts-world-2022465x310.jpg" crc="360376903" seo="true" ref="index">
      <caption webpage="index" alt=""/>
    </file>
    <file name="23ticket-vip-fri127x127.jpg" crc="3814935356" seo="true" ref="index">
      <caption webpage="index" alt=""/>
    </file>
    <file name="23ticket-vip-sat127x127.jpg" crc="469910270" seo="true" ref="index">
      <caption webpage="index" alt=""/>
    </file>
    <file name="23ticket-ga-fri127x127.jpg" crc="229638649" seo="true" ref="index">
      <caption webpage="index" alt=""/>
    </file>
    <file name="23ticket-ga-sat127x127.jpg" crc="85434753" seo="true" ref="index">
      <caption webpage="index" alt=""/>
    </file>
    <file name="resorts-world-2022384x256.jpg" crc="180425353" seo="true" ref="index">
      <caption webpage="index" alt=""/>
    </file>
    <file name="resorts-world-2022326x217.jpg" crc="4130956360" seo="true" ref="index">
      <caption webpage="index" alt=""/>
    </file>
    <file name="23ticket-vip-fri164x164.jpg" crc="4247365359" seo="true" ref="index">
      <caption webpage="index" alt=""/>
    </file>
    <file name="23ticket-vip-sat164x164.jpg" crc="4211986702" seo="true" ref="index">
      <caption webpage="index" alt=""/>
    </file>
    <file name="23ticket-ga-fri164x164.jpg" crc="3767475339" seo="true" ref="index">
      <caption webpage="index" alt=""/>
    </file>
    <file name="23ticket-ga-sat164x164.jpg" crc="359326505" seo="true" ref="index">
      <caption webpage="index" alt=""/>
    </file>
    <file name="resorts-world-2022321x214.jpg" crc="111118115" seo="true" ref="index">
      <caption webpage="index" alt=""/>
    </file>
    <file name="23ticket-vip-fri136x136.jpg" crc="141234420" seo="true" ref="index">
      <caption webpage="index" alt=""/>
    </file>
    <file name="23ticket-vip-sat136x136.jpg" crc="386488034" seo="true" ref="index">
      <caption webpage="index" alt=""/>
    </file>
    <file name="23ticket-ga-fri136x136.jpg" crc="4227911647" seo="true" ref="index">
      <caption webpage="index" alt=""/>
    </file>
    <file name="23ticket-ga-sat136x136.jpg" crc="410755800" seo="true" ref="index">
      <caption webpage="index" alt=""/>
    </file>
    <file name="resorts-world-2022258x172.jpg" crc="285148440" seo="true" ref="index">
      <caption webpage="index" alt=""/>
    </file>
    <file name="top3images-new.jpg" crc="351806434" seo="true" ref="index:faq">
      <caption webpage="index" alt=""/>
      <caption webpage="faq" alt=""/>
    </file>
    <file name="logos.jpg" crc="4167564703" seo="true" ref="index">
      <caption webpage="index" alt=""/>
    </file>
    <file name="top3images-new1200x217.jpg" crc="342855148" seo="true" ref="index:faq">
      <caption webpage="index" alt=""/>
      <caption webpage="faq" alt=""/>
    </file>
    <file name="smoke4216x627.png" crc="4133159776" seo="true" ref="index">
      <caption webpage="index" alt=""/>
    </file>
    <file name="23ticket-vip-fri253x253.jpg" crc="4265309843" seo="true" ref="index">
      <caption webpage="index" alt=""/>
    </file>
    <file name="23ticket-vip-sat253x253.jpg" crc="142496790" seo="true" ref="index">
      <caption webpage="index" alt=""/>
    </file>
    <file name="23ticket-ga-fri253x253.jpg" crc="4216394462" seo="true" ref="index">
      <caption webpage="index" alt=""/>
    </file>
    <file name="23ticket-ga-sat253x253.jpg" crc="457235341" seo="true" ref="index">
      <caption webpage="index" alt=""/>
    </file>
    <file name="resorts-world-2022512x342.jpg" crc="373858893" seo="true" ref="index">
      <caption webpage="index" alt=""/>
    </file>
    <file name="bot3images1200x295.jpg" crc="4278901807" seo="true" ref="index">
      <caption webpage="index" alt=""/>
    </file>
    <file name="top3images-new1024x186.jpg" crc="480431101" seo="true" ref="index:faq">
      <caption webpage="index" alt=""/>
      <caption webpage="faq" alt=""/>
    </file>
    <file name="top3images-new960x174.jpg" crc="443490680" seo="true" ref="index:faq">
      <caption webpage="index" alt=""/>
      <caption webpage="faq" alt=""/>
    </file>
    <file name="top3images-new850x154.jpg" crc="521734487" seo="true" ref="index:faq">
      <caption webpage="index" alt=""/>
      <caption webpage="faq" alt=""/>
    </file>
    <file name="top3images-new768x139.jpg" crc="4076128489" seo="true" ref="index:faq">
      <caption webpage="index" alt=""/>
      <caption webpage="faq" alt=""/>
    </file>
    <file name="top3images-new667x121.jpg" crc="3909004626" seo="true" ref="index:faq">
      <caption webpage="index" alt=""/>
      <caption webpage="faq" alt=""/>
    </file>
    <file name="top3images-new568x103.jpg" crc="80904515" seo="true" ref="index:faq">
      <caption webpage="index" alt=""/>
      <caption webpage="faq" alt=""/>
    </file>
    <file name="top3images-mobile-new414x686.jpg" crc="3790702091" seo="true" ref="index:faq">
      <caption webpage="index" alt=""/>
      <caption webpage="faq" alt=""/>
    </file>
    <file name="top3images-mobile-new375x622.jpg" crc="3927717667" seo="true" ref="index:faq">
      <caption webpage="index" alt=""/>
      <caption webpage="faq" alt=""/>
    </file>
    <file name="top3images-mobile-new320x530.jpg" crc="124709182" seo="true" ref="index:faq">
      <caption webpage="index" alt=""/>
      <caption webpage="faq" alt=""/>
    </file>
    <file name="top3images-new1680x304.jpg" crc="4270555671" seo="true" ref="index:faq">
      <caption webpage="index" alt=""/>
      <caption webpage="faq" alt=""/>
    </file>
    <file name="23ticket-vip-fri354x354.jpg" crc="4281319792" seo="true" ref="index">
      <caption webpage="index" alt=""/>
    </file>
    <file name="23ticket-vip-sat354x354.jpg" crc="304806921" seo="true" ref="index">
      <caption webpage="index" alt=""/>
    </file>
    <file name="23ticket-ga-fri354x354.jpg" crc="332904395" seo="true" ref="index">
      <caption webpage="index" alt=""/>
    </file>
    <file name="23ticket-ga-sat354x354.jpg" crc="3860544935" seo="true" ref="index">
      <caption webpage="index" alt=""/>
    </file>
    <file name="logos1023x1648.jpg" crc="512977342" seo="true" ref="index">
      <caption webpage="index" alt=""/>
    </file>
    <file name="resorts-world-2022717x479.jpg" crc="32451107" seo="true" ref="index">
      <caption webpage="index" alt=""/>
    </file>
    <file name="bot3images1680x413.jpg" crc="19366477" seo="true" ref="index">
      <caption webpage="index" alt=""/>
    </file>
    <file name="top3images-new1450x263.jpg" crc="4006088237" seo="true" ref="index:faq">
      <caption webpage="index" alt=""/>
      <caption webpage="faq" alt=""/>
    </file>
    <file name="smoke4261x757.png" crc="4133159776" seo="true" ref="index">
      <caption webpage="index" alt=""/>
    </file>
    <file name="23ticket-vip-fri306x306.jpg" crc="342302147" seo="true" ref="index">
      <caption webpage="index" alt=""/>
    </file>
    <file name="23ticket-vip-sat306x306.jpg" crc="4207303551" seo="true" ref="index">
      <caption webpage="index" alt=""/>
    </file>
    <file name="23ticket-ga-fri306x306.jpg" crc="4274529743" seo="true" ref="index">
      <caption webpage="index" alt=""/>
    </file>
    <file name="23ticket-ga-sat306x306.jpg" crc="3819432473" seo="true" ref="index">
      <caption webpage="index" alt=""/>
    </file>
    <file name="logos883x1423.jpg" crc="3837676110" seo="true" ref="index">
      <caption webpage="index" alt=""/>
    </file>
    <file name="resorts-world-2022619x413.jpg" crc="3791739753" seo="true" ref="index">
      <caption webpage="index" alt=""/>
    </file>
    <file name="bot3images1450x357.jpg" crc="4094276892" seo="true" ref="index">
      <caption webpage="index" alt=""/>
    </file>
    <file name="ultimate-weekend.png" crc="184727470" seo="true" ref="index:faq">
      <caption webpage="index" alt=""/>
      <caption webpage="faq" alt=""/>
    </file>
    <file name="ultimate-weekend1420x174.png" crc="184727470" seo="true" ref="index:faq">
      <caption webpage="index" alt=""/>
      <caption webpage="faq" alt=""/>
    </file>
    <file name="ultimate-weekend1225x150.png" crc="4085805133" seo="true" ref="index:faq">
      <caption webpage="index" alt=""/>
      <caption webpage="faq" alt=""/>
    </file>
    <file name="ultimate-weekend1014x125.png" crc="3837435830" seo="true" ref="index:faq">
      <caption webpage="index" alt=""/>
      <caption webpage="faq" alt=""/>
    </file>
    <file name="ultimate-weekend866x106.png" crc="4165331352" seo="true" ref="index:faq">
      <caption webpage="index" alt=""/>
      <caption webpage="faq" alt=""/>
    </file>
    <file name="23ticket-vip-fri221x221.jpg" crc="3817899269" seo="true" ref="index">
      <caption webpage="index" alt=""/>
    </file>
    <file name="23ticket-ga-fri221x221.jpg" crc="4014512179" seo="true" ref="index">
      <caption webpage="index" alt=""/>
    </file>
    <file name="23ticket-vip-sat221x221.jpg" crc="52444688" seo="true" ref="index">
      <caption webpage="index" alt=""/>
    </file>
    <file name="23ticket-ga-sat221x221.jpg" crc="497923096" seo="true" ref="index">
      <caption webpage="index" alt=""/>
    </file>
    <file name="ultimate-weekend811x100.png" crc="4004472624" seo="true" ref="index:faq">
      <caption webpage="index" alt=""/>
      <caption webpage="faq" alt=""/>
    </file>
    <file name="ultimate-weekend719x88.png" crc="3893275891" seo="true" ref="index:faq">
      <caption webpage="index" alt=""/>
      <caption webpage="faq" alt=""/>
    </file>
    <file name="ultimate-weekend649x80.png" crc="334286697" seo="true" ref="index:faq">
      <caption webpage="index" alt=""/>
      <caption webpage="faq" alt=""/>
    </file>
    <file name="ultimate-weekend564x69.png" crc="3815088317" seo="true" ref="index:faq">
      <caption webpage="index" alt=""/>
      <caption webpage="faq" alt=""/>
    </file>
    <file name="ultimate-weekend480x59.png" crc="391604832" seo="true" ref="index:faq">
      <caption webpage="index" alt=""/>
      <caption webpage="faq" alt=""/>
    </file>
    <file name="ultimate-weekend-mobile.png" crc="321079377" seo="true" ref="index">
      <caption webpage="index" alt=""/>
      <caption webpage="faq" alt=""/>
    </file>
    <file name="ultimate-weekend-mobile_2x.png" crc="481669193" seo="true" ref="index">
      <caption webpage="index" alt=""/>
      <caption webpage="faq" alt=""/>
    </file>
    <file name="ultimate-weekend-mobile336x131.png" crc="97202301" seo="true" ref="index:faq">
      <caption webpage="index" alt=""/>
      <caption webpage="faq" alt=""/>
    </file>
    <file name="ultimate-weekend-mobile336x131_2x.png" crc="198051837" seo="true" ref="index:faq">
      <caption webpage="index" alt=""/>
      <caption webpage="faq" alt=""/>
    </file>
    <file name="ultimate-weekend-mobile286x112.png" crc="192403647" seo="true" ref="index:faq">
      <caption webpage="index" alt=""/>
      <caption webpage="faq" alt=""/>
    </file>
    <file name="ultimate-weekend-mobile286x112_2x.png" crc="3801565047" seo="true" ref="index:faq">
      <caption webpage="index" alt=""/>
      <caption webpage="faq" alt=""/>
    </file>
    <file name="top3images-new1610x292.jpg" crc="4079292124" seo="true" ref="index">
      <caption webpage="index" alt=""/>
    </file>
    <file name="ultimate-weekend1361x167.png" crc="3942208404" seo="true" ref="index">
      <caption webpage="index" alt=""/>
    </file>
    <file name="smoke4290x841.png" crc="4133159776" seo="true" ref="index">
      <caption webpage="index" alt=""/>
    </file>
    <file name="23ticket-vip-fri339x339.jpg" crc="4177322000" seo="true" ref="index">
      <caption webpage="index" alt=""/>
    </file>
    <file name="23ticket-ga-fri339x339.jpg" crc="4236156163" seo="true" ref="index">
      <caption webpage="index" alt=""/>
    </file>
    <file name="23ticket-vip-sat339x339.jpg" crc="445854754" seo="true" ref="index">
      <caption webpage="index" alt=""/>
    </file>
    <file name="23ticket-ga-sat339x339.jpg" crc="238298514" seo="true" ref="index">
      <caption webpage="index" alt=""/>
    </file>
    <file name="logos981x1580.jpg" crc="82961183" seo="true" ref="index">
      <caption webpage="index" alt=""/>
    </file>
    <file name="resorts-world-2022687x459.jpg" crc="4108766930" seo="true" ref="index">
      <caption webpage="index" alt=""/>
    </file>
    <file name="bot3images1610x396.jpg" crc="275963971" seo="true" ref="index">
      <caption webpage="index" alt=""/>
    </file>
    <file name="mid3images-new2.jpg" crc="444850687" seo="true" ref="index">
      <caption webpage="index" alt=""/>
    </file>
    <file name="mid3images-new21680x415.jpg" crc="4224670632" seo="true" ref="index">
      <caption webpage="index" alt=""/>
    </file>
    <file name="mid3images-new21610x398.jpg" crc="305458341" seo="true" ref="index">
      <caption webpage="index" alt=""/>
    </file>
    <file name="mid3images-new21450x358.jpg" crc="4096918311" seo="true" ref="index">
      <caption webpage="index" alt=""/>
    </file>
    <file name="mid3images-new21200x297.jpg" crc="245400900" seo="true" ref="index">
      <caption webpage="index" alt=""/>
    </file>
    <file name="mid3images-new21024x253.jpg" crc="4149773580" seo="true" ref="index">
      <caption webpage="index" alt=""/>
    </file>
    <file name="mid3images-new2960x237.jpg" crc="149723676" seo="true" ref="index">
      <caption webpage="index" alt=""/>
    </file>
    <file name="mid3images-new2850x210.jpg" crc="4275963317" seo="true" ref="index">
      <caption webpage="index" alt=""/>
    </file>
    <file name="mid3images-new2768x190.jpg" crc="422092902" seo="true" ref="index">
      <caption webpage="index" alt=""/>
    </file>
    <file name="mid3images-new2667x165.jpg" crc="4093725378" seo="true" ref="index">
      <caption webpage="index" alt=""/>
    </file>
    <file name="mid3images-new2568x141.jpg" crc="197606520" seo="true" ref="index">
      <caption webpage="index" alt=""/>
    </file>
    <file name="mid3images-mobile-new2414x938.jpg" crc="397472168" seo="true" ref="index">
      <caption webpage="index" alt=""/>
    </file>
    <file name="mid3images-mobile-new2375x850.jpg" crc="4002557807" seo="true" ref="index">
      <caption webpage="index" alt=""/>
    </file>
    <file name="mid3images-mobile-new2320x725.jpg" crc="4124084355" seo="true" ref="index">
      <caption webpage="index" alt=""/>
    </file>
    <file name="23silverb.jpg" crc="337059970" seo="true" ref="index">
      <caption webpage="index" alt=""/>
    </file>
    <file name="23goldb.jpg" crc="3862180723" seo="true" ref="index">
      <caption webpage="index" alt=""/>
    </file>
    <file name="23silverb354x354.jpg" crc="4125253454" seo="true" ref="index">
      <caption webpage="index" alt=""/>
    </file>
    <file name="23goldb354x354.jpg" crc="3915485958" seo="true" ref="index">
      <caption webpage="index" alt=""/>
    </file>
    <file name="23silverb339x339.jpg" crc="192012907" seo="true" ref="index">
      <caption webpage="index" alt=""/>
    </file>
    <file name="23goldb339x339.jpg" crc="3859153082" seo="true" ref="index">
      <caption webpage="index" alt=""/>
    </file>
    <file name="23silverb306x306.jpg" crc="4077790794" seo="true" ref="index">
      <caption webpage="index" alt=""/>
    </file>
    <file name="23goldb306x306.jpg" crc="242216316" seo="true" ref="index">
      <caption webpage="index" alt=""/>
    </file>
    <file name="23silverb253x253.jpg" crc="3791565111" seo="true" ref="index">
      <caption webpage="index" alt=""/>
    </file>
    <file name="23goldb253x253.jpg" crc="4278641334" seo="true" ref="index">
      <caption webpage="index" alt=""/>
    </file>
    <file name="23silverb221x221.jpg" crc="3776112731" seo="true" ref="index">
      <caption webpage="index" alt=""/>
    </file>
    <file name="23goldb221x221.jpg" crc="197250483" seo="true" ref="index">
      <caption webpage="index" alt=""/>
    </file>
    <file name="23silverb216x216.jpg" crc="3815572919" seo="true" ref="index">
      <caption webpage="index" alt=""/>
    </file>
    <file name="23goldb216x216.jpg" crc="366950949" seo="true" ref="index">
      <caption webpage="index" alt=""/>
    </file>
    <file name="23silverb176x176.jpg" crc="137117121" seo="true" ref="index">
      <caption webpage="index" alt=""/>
    </file>
    <file name="23goldb176x176.jpg" crc="96163063" seo="true" ref="index">
      <caption webpage="index" alt=""/>
    </file>
    <file name="23silverb170x170.jpg" crc="187388937" seo="true" ref="index">
      <caption webpage="index" alt=""/>
    </file>
    <file name="23goldb170x170.jpg" crc="204027627" seo="true" ref="index">
      <caption webpage="index" alt=""/>
    </file>
    <file name="23silverb141x141.jpg" crc="4216497563" seo="true" ref="index">
      <caption webpage="index" alt=""/>
    </file>
    <file name="23goldb141x141.jpg" crc="145470831" seo="true" ref="index">
      <caption webpage="index" alt=""/>
    </file>
    <file name="23silverb127x127.jpg" crc="263195821" seo="true" ref="index">
      <caption webpage="index" alt=""/>
    </file>
    <file name="23goldb127x127.jpg" crc="4272507971" seo="true" ref="index">
      <caption webpage="index" alt=""/>
    </file>
    <file name="23silverb200x200.jpg" crc="277791709" seo="true" ref="index">
      <caption webpage="index" alt=""/>
    </file>
    <file name="23goldb200x200.jpg" crc="209664378" seo="true" ref="index">
      <caption webpage="index" alt=""/>
    </file>
    <file name="23silverb180x180.jpg" crc="4165930644" seo="true" ref="index">
      <caption webpage="index" alt=""/>
    </file>
    <file name="23goldb180x180.jpg" crc="3932416769" seo="true" ref="index">
      <caption webpage="index" alt=""/>
    </file>
    <file name="23silverb150x150.jpg" crc="87277266" seo="true" ref="index">
      <caption webpage="index" alt=""/>
    </file>
    <file name="23goldb150x150.jpg" crc="69357399" seo="true" ref="index">
      <caption webpage="index" alt=""/>
    </file>
    <file name="faq-pic.jpg" crc="4157082050" ref="faq">
      <caption webpage="faq" alt=""/>
    </file>
    <file name="faq-pic-u49600-fr.jpg" crc="158422912" ref="faq"/>
    <file name="faq-pic-u49600-fr_2x.jpg" crc="3916032526" ref="faq"/>
    <file name="smoke.jpg" crc="4050536624" ref="index:faq">
      <caption webpage="index" alt=""/>
      <caption webpage="faq" alt=""/>
    </file>
    <file name="bslv23-header-new2-crop-u28903.png" crc="146387370" seo="true" ref="index:faq">
      <caption webpage="index" alt=""/>
      <caption webpage="index" alt=""/>
      <caption webpage="index" alt=""/>
      <caption webpage="index" alt=""/>
      <caption webpage="index" alt=""/>
      <caption webpage="index" alt=""/>
      <caption webpage="index" alt=""/>
      <caption webpage="index" alt=""/>
      <caption webpage="index" alt=""/>
      <caption webpage="index" alt=""/>
      <caption webpage="index" alt=""/>
      <caption webpage="index" alt=""/>
      <caption webpage="index" alt=""/>
      <caption webpage="index" alt=""/>
      <caption webpage="index" alt=""/>
      <caption webpage="index" alt=""/>
      <caption webpage="index" alt=""/>
      <caption webpage="faq" alt=""/>
      <caption webpage="faq" alt=""/>
      <caption webpage="faq" alt=""/>
      <caption webpage="faq" alt=""/>
      <caption webpage="faq" alt=""/>
      <caption webpage="faq" alt=""/>
      <caption webpage="faq" alt=""/>
      <caption webpage="faq" alt=""/>
      <caption webpage="faq" alt=""/>
      <caption webpage="faq" alt=""/>
      <caption webpage="faq" alt=""/>
      <caption webpage="faq" alt=""/>
      <caption webpage="faq" alt=""/>
      <caption webpage="faq" alt=""/>
    </file>
    <file name="smoke2.jpg" crc="3912667438" ref="index:faq">
      <caption webpage="index" alt=""/>
      <caption webpage="faq" alt=""/>
    </file>
    <file name="smoke_2x.jpg" crc="4050536624" ref="index:faq">
      <caption webpage="index" alt=""/>
      <caption webpage="faq" alt=""/>
    </file>
    <file name="ultimate-weekend-mobile371x145.png" crc="3836949857" seo="true" ref="index:faq">
      <caption webpage="index" alt=""/>
      <caption webpage="faq" alt=""/>
    </file>
    <file name="ultimate-weekend-mobile371x145_2x.png" crc="481669193" seo="true" ref="index:faq">
      <caption webpage="index" alt=""/>
      <caption webpage="faq" alt=""/>
    </file>
    <file name="top3images-mobile-new390x646.jpg" crc="3979281161" seo="true" ref="index">
      <caption webpage="index" alt=""/>
    </file>
    <file name="ultimate-weekend-mobile349x136.png" crc="3855564317" seo="true" ref="index">
      <caption webpage="index" alt=""/>
    </file>
    <file name="ultimate-weekend-mobile349x136_2x.png" crc="4001612472" seo="true" ref="index">
      <caption webpage="index" alt=""/>
    </file>
    <file name="23silverb188x188.jpg" crc="510546288" seo="true" ref="index">
      <caption webpage="index" alt=""/>
    </file>
    <file name="23goldb188x188.jpg" crc="342780113" seo="true" ref="index">
      <caption webpage="index" alt=""/>
    </file>
    <file name="mid3images-mobile-new2390x884.jpg" crc="3949510288" seo="true" ref="index">
      <caption webpage="index" alt=""/>
    </file>
    <file name="resorts-world-2022334x223.jpg" crc="4010821669" seo="true" ref="index">
      <caption webpage="index" alt=""/>
    </file>
    <file name="bot3images-mobile390x884.jpg" crc="305257946" seo="true" ref="index">
      <caption webpage="index" alt=""/>
    </file>
    <file name="logos-mobile-crop-u471024.jpg" crc="263938169" seo="true" ref="index">
      <caption webpage="index" alt=""/>
    </file>
    <file name="logos-mobile-crop-u47102_2x4.jpg" crc="64292209" seo="true" ref="index">
      <caption webpage="index" alt=""/>
    </file>
    <file name="bslv23-header-new2320x176.png" crc="468815200" seo="true" ref="index:faq">
      <caption webpage="index" alt=""/>
      <caption webpage="faq" alt=""/>
    </file>
    <file name="bslv23-header-new2320x176_2x.png" crc="405358343" seo="true" ref="index:faq">
      <caption webpage="index" alt=""/>
      <caption webpage="faq" alt=""/>
    </file>
    <file name="logos-mobile-crop-u471025.jpg" crc="3947335638" seo="true" ref="index">
      <caption webpage="index" alt=""/>
    </file>
    <file name="logos-mobile-crop-u47102_2x5.jpg" crc="134383333" seo="true" ref="index">
      <caption webpage="index" alt=""/>
    </file>
    <file name="ultimate-weekend438x54.png" crc="3870699736" seo="true" ref="index:faq">
      <caption webpage="index" alt=""/>
      <caption webpage="faq" alt=""/>
    </file>
    <file name="smoke494x271.png" crc="4278537056" seo="true" ref="index">
      <caption webpage="index" alt=""/>
    </file>
    <file name="23silverb116x116.jpg" crc="4281518157" seo="true" ref="index">
      <caption webpage="index" alt=""/>
    </file>
    <file name="23goldb116x116.jpg" crc="391360986" seo="true" ref="index">
      <caption webpage="index" alt=""/>
    </file>
    <file name="23ticket-vip-fri116x116.jpg" crc="411593875" seo="true" ref="index">
      <caption webpage="index" alt=""/>
    </file>
    <file name="23ticket-ga-fri116x116.jpg" crc="50405013" seo="true" ref="index">
      <caption webpage="index" alt=""/>
    </file>
    <file name="23ticket-vip-sat116x116.jpg" crc="3879484242" seo="true" ref="index">
      <caption webpage="index" alt=""/>
    </file>
    <file name="23ticket-ga-sat116x116.jpg" crc="246692234" seo="true" ref="index">
      <caption webpage="index" alt=""/>
    </file>
    <file name="logos426x686.jpg" crc="4224519088" seo="true" ref="index">
      <caption webpage="index" alt=""/>
    </file>
    <file name="resorts-world-2022350x234.jpg" crc="68923314" seo="true" ref="index">
      <caption webpage="index" alt=""/>
    </file>
    <file name="ultimate-weekend406x50.png" crc="3764671684" seo="true" ref="index:faq">
      <caption webpage="index" alt=""/>
      <caption webpage="faq" alt=""/>
    </file>
    <file name="top3images-new480x87.jpg" crc="4050736890" seo="true" ref="index:faq">
      <caption webpage="index" alt=""/>
      <caption webpage="faq" alt=""/>
    </file>
    <file name="smoke487x251.png" crc="168120489" seo="true" ref="index">
      <caption webpage="index" alt=""/>
    </file>
    <file name="23silverb107x107.jpg" crc="105499829" seo="true" ref="index">
      <caption webpage="index" alt=""/>
    </file>
    <file name="23goldb107x107.jpg" crc="427897761" seo="true" ref="index">
      <caption webpage="index" alt=""/>
    </file>
    <file name="23ticket-vip-fri107x107.jpg" crc="4215764153" seo="true" ref="index">
      <caption webpage="index" alt=""/>
    </file>
    <file name="23ticket-ga-fri107x107.jpg" crc="472565544" seo="true" ref="index">
      <caption webpage="index" alt=""/>
    </file>
    <file name="23ticket-vip-sat107x107.jpg" crc="412519965" seo="true" ref="index">
      <caption webpage="index" alt=""/>
    </file>
    <file name="23ticket-ga-sat107x107.jpg" crc="458572618" seo="true" ref="index">
      <caption webpage="index" alt=""/>
    </file>
    <file name="mid3images-new2480x119.jpg" crc="4259749486" seo="true" ref="index">
      <caption webpage="index" alt=""/>
    </file>
    <file name="logos395x635.jpg" crc="383149286" seo="true" ref="index">
      <caption webpage="index" alt=""/>
    </file>
    <file name="resorts-world-2022324x217.jpg" crc="207152877" seo="true" ref="index">
      <caption webpage="index" alt=""/>
    </file>
    <file name="bot3images480x119.jpg" crc="165304051" seo="true" ref="index">
      <caption webpage="index" alt=""/>
    </file>
    <file name="top3images-mobile-new430x713.jpg" crc="303504969" seo="true" ref="index">
      <caption webpage="index" alt=""/>
    </file>
    <file name="23silverb208x208.jpg" crc="24370146" seo="true" ref="index">
      <caption webpage="index" alt=""/>
    </file>
    <file name="23goldb208x208.jpg" crc="3824622174" seo="true" ref="index">
      <caption webpage="index" alt=""/>
    </file>
    <file name="23ticket-vip-fri183x183.jpg" crc="192273738" seo="true" ref="index">
      <caption webpage="index" alt=""/>
    </file>
    <file name="23ticket-ga-fri183x183.jpg" crc="4121727696" seo="true" ref="index">
      <caption webpage="index" alt=""/>
    </file>
    <file name="23ticket-vip-sat183x183.jpg" crc="3781447378" seo="true" ref="index">
      <caption webpage="index" alt=""/>
    </file>
    <file name="23ticket-ga-sat183x183.jpg" crc="93754434" seo="true" ref="index">
      <caption webpage="index" alt=""/>
    </file>
    <file name="mid3images-mobile-new2430x974.jpg" crc="278635580" seo="true" ref="index">
      <caption webpage="index" alt=""/>
    </file>
    <file name="resorts-world-2022338x226.jpg" crc="343376790" seo="true" ref="index">
      <caption webpage="index" alt=""/>
    </file>
    <file name="bot3images-mobile430x974.jpg" crc="3869093781" seo="true" ref="index">
      <caption webpage="index" alt=""/>
    </file>
    <file name="23aab-so.jpg" crc="4258318663" seo="true" ref="index">
      <caption webpage="index" alt=""/>
    </file>
    <file name="23aab-so354x354.jpg" crc="4087664145" seo="true" ref="index">
      <caption webpage="index" alt=""/>
    </file>
    <file name="23aab-so339x339.jpg" crc="3993745644" seo="true" ref="index">
      <caption webpage="index" alt=""/>
    </file>
    <file name="23aab-so306x306.jpg" crc="188528655" seo="true" ref="index">
      <caption webpage="index" alt=""/>
    </file>
    <file name="23aab-so253x253.jpg" crc="383130727" seo="true" ref="index">
      <caption webpage="index" alt=""/>
    </file>
    <file name="23aab-so221x221.jpg" crc="274023962" seo="true" ref="index">
      <caption webpage="index" alt=""/>
    </file>
    <file name="23aab-so216x216.jpg" crc="209465291" seo="true" ref="index">
      <caption webpage="index" alt=""/>
    </file>
    <file name="23aab-so176x176.jpg" crc="3895329826" seo="true" ref="index">
      <caption webpage="index" alt=""/>
    </file>
    <file name="23aab-so170x170.jpg" crc="393779250" seo="true" ref="index">
      <caption webpage="index" alt=""/>
    </file>
    <file name="23aab-so141x141.jpg" crc="124366417" seo="true" ref="index">
      <caption webpage="index" alt=""/>
    </file>
    <file name="23aab-so127x127.jpg" crc="3912418093" seo="true" ref="index">
      <caption webpage="index" alt=""/>
    </file>
    <file name="top3images-new519x94.jpg" crc="23987644" seo="true" ref="index">
      <caption webpage="index" alt=""/>
    </file>
    <file name="23aab-so116x116.jpg" crc="232676924" seo="true" ref="index">
      <caption webpage="index" alt=""/>
    </file>
    <file name="mid3images-new2519x128.jpg" crc="79826229" seo="true" ref="index">
      <caption webpage="index" alt=""/>
    </file>
    <file name="bot3images519x128.jpg" crc="4193538179" seo="true" ref="index">
      <caption webpage="index" alt=""/>
    </file>
    <file name="23aab-so107x107.jpg" crc="352935874" seo="true" ref="index">
      <caption webpage="index" alt=""/>
    </file>
    <file name="23aab-so208x208.jpg" crc="3914444801" seo="true" ref="index">
      <caption webpage="index" alt=""/>
    </file>
    <file name="23aab-so200x200.jpg" crc="11268882" seo="true" ref="index">
      <caption webpage="index" alt=""/>
    </file>
    <file name="23aab-so188x188.jpg" crc="289856581" seo="true" ref="index">
      <caption webpage="index" alt=""/>
    </file>
    <file name="23aab-so180x180.jpg" crc="475603368" seo="true" ref="index">
      <caption webpage="index" alt=""/>
    </file>
    <file name="23aab-so150x150.jpg" crc="376137513" seo="true" ref="index">
      <caption webpage="index" alt=""/>
    </file>
    <file name="top3images-new518x94.jpg" crc="23987644" seo="true" ref="faq">
      <caption webpage="faq" alt=""/>
    </file>
  </folder>
  <file name="index.html" crc="42824543" seo="true" mt="1689001173152" redirect="true"/>
  <file name="faq.html" crc="506003018" seo="true" mt="1689699807413" redirect="true"/>
</manifest>